update_MisFotos.py
folder_backup/__init__.py
folder_backup/file_handling.py
folder_backup/md5.py
folder_backup/mirror.py
folder_backup-0.1.6.dist-info/LICENSE
folder_backup-0.1.6.dist-info/METADATA
folder_backup-0.1.6.dist-info/WHEEL
folder_backup-0.1.6.dist-info/top_level.txt
folder_backup-0.1.6.dist-info/RECORD
